setup.py
gpxutils/__init__.py
gpxutils/gpxclean.py
gpxutils/gpxpull.py
gpxutils.egg-info/PKG-INFO
gpxutils.egg-info/SOURCES.txt
gpxutils.egg-info/dependency_links.txt
gpxutils.egg-info/entry_points.txt
gpxutils.egg-info/requires.txt
gpxutils.egg-info/top_level.txt