Metadata-Version: 1.1
Name: gpxutils
Version: 2.0.2
Summary: Tools for working with GPX files
Home-page: https://github.com/emenendez/gpxutils
Author: Eric Menendez
Author-email: ericmenendez@gmail.com
License: AGPLv3+
Keywords: gpx gps geo spatial utilities
Platform: UNKNOWN
Classifier: Development Status :: 5 - Production/Stable
Classifier: Intended Audience :: Developers
Classifier: Intended Audience :: Other Audience
Classifier: Topic :: Utilities
Classifier: License :: OSI Approved :: GNU Affero General Public License v3 or later (AGPLv3+)
Classifier: Programming Language :: Python :: 3.4
